agipy/__init__.py
agipy/agipy.py
agipy/test_agipy.py
agipy/providers/__init__.py
agipy/providers/azure.py
agipy/providers/test_azure.py
agipy-0.2.2.dist-info/LICENSE
agipy-0.2.2.dist-info/METADATA
agipy-0.2.2.dist-info/WHEEL
agipy-0.2.2.dist-info/entry_points.txt
agipy-0.2.2.dist-info/top_level.txt
agipy-0.2.2.dist-info/RECORD
