Metadata-Version: 2.1
Name: agipy
Version: 0.2.2
Summary: destroy cloud infrastructure in a hurry
Home-page: https://github.com/shimst3r/agipy
Author: Nils P. Müller
Author-email: shimst3r@gmail.com
License: GPL
Download-URL: https://github.com/shimst3r/agipy/archive/0.2.2.tar.gz
Keywords: azure,cli,cloud,devops,sysadmin,tool
Platform: UNKNOWN
Classifier: Development Status :: 3 - Alpha
Classifier: Intended Audience :: Developers
Classifier: License :: OSI Approved :: GNU General Public License v3 (GPLv3)
Classifier: Programming Language :: Python :: 3
Classifier: Programming Language :: Python :: 3.7
Classifier: Programming Language :: Python :: 3.8
Requires-Python: >=3.7
Requires-Dist: azure-common
Requires-Dist: azure-mgmt-resource
Requires-Dist: msrestazure
Requires-Dist: Click
